approck_fastapi_utils/__init__.py
approck_fastapi_utils/auth.py
approck_fastapi_utils/exception_handlers.py
approck_fastapi_utils/exceptions.py
approck_fastapi_utils/jwt.py
approck_fastapi_utils/response.py
approck_fastapi_utils/responses.py
approck_fastapi_utils/sqlalchemy/__init__.py
approck_fastapi_utils/sqlalchemy/exception_handlers.py
approck_fastapi_utils/types.py
approck_fastapi_utils-0.1.10.dist-info/METADATA
approck_fastapi_utils-0.1.10.dist-info/WHEEL
approck_fastapi_utils-0.1.10.dist-info/RECORD
