Metadata-Version: 2.3
Name: approck-fastapi-utils
Version: 0.1.10
Summary: 
Author: Aleksey Dalekin
Author-email: ald@approck.pro
Requires-Python: >=3.10,<4.0
Classifier: Programming Language :: Python :: 3
Classifier: Programming Language :: Python :: 3.10
Classifier: Programming Language :: Python :: 3.11
Classifier: Programming Language :: Python :: 3.12
Classifier: Programming Language :: Python :: 3.13
Requires-Dist: fastapi (>=0.109.2)
Requires-Dist: pydantic (>=2.4.1)
